{
  "_fv": 18,
  "_type": "food",
  "definition": {
    "renderType": 0,
    "texture": "lolipop_green",
    "customModelName": "Normal",
    "name": "Lolipop",
    "rarity": "COMMON",
    "specialInfo": [],
    "creativeTab": {
      "value": "CUSTOM:ASweetToothsFantasy"
    },
    "stackSize": 1,
    "nutritionalValue": 5,
    "saturation": 0.3,
    "eatingSpeed": 32,
    "resultItem": {
      "value": "Items.STICK"
    },
    "forDogs": false,
    "isAlwaysEdible": false,
    "animation": "eat",
    "hasGlow": false
  }
}